molesq/__init__.py
molesq/image.py
molesq/transform.py
molesq/utils.py
molesq/version.py
molesq-0.4.0.dist-info/LICENSE
molesq-0.4.0.dist-info/METADATA
molesq-0.4.0.dist-info/WHEEL
molesq-0.4.0.dist-info/top_level.txt
molesq-0.4.0.dist-info/RECORD
