Metadata-Version: 2.1
Name: molesq
Version: 0.4.0
Summary: Implementation of moving least squares for ND point and image deformation
Home-page: https://github.com/clbarnes/molesq
Author: Chris L. Barnes
License: UNKNOWN
Platform: UNKNOWN
Classifier: Development Status :: 3 - Alpha
Classifier: License :: OSI Approved :: MIT License
Classifier: Programming Language :: Python :: 3.7
Classifier: Programming Language :: Python :: 3.8
Classifier: Programming Language :: Python :: 3.9
Requires-Python: >=3.7, <4.0
License-File: LICENSE
